{
"meta":{"test_sets":[],"test_metrics":[],"learn_metrics":[{"best_value":"Min","name":"RMSE"}],"launch_mode":"Train","parameters":"","iteration_count":200,"learn_sets":["learn"],"name":"experiment"},
"iterations":[
{"learn":[58.38881782],"iteration":0,"passed_time":0.1395056398,"remaining_time":27.76162233},
{"learn":[56.10041456],"iteration":1,"passed_time":0.1397112565,"remaining_time":13.83141439},
{"learn":[53.80938425],"iteration":2,"passed_time":0.1398824588,"remaining_time":9.185614792},
{"learn":[51.65204763],"iteration":3,"passed_time":0.1401095099,"remaining_time":6.865365986},
{"learn":[49.69833566],"iteration":4,"passed_time":0.1402715812,"remaining_time":5.470591666},
{"learn":[47.63069826],"iteration":5,"passed_time":0.1404352413,"remaining_time":4.540739469},
{"learn":[45.82588832],"iteration":6,"passed_time":0.1405584833,"remaining_time":3.875398181},
{"learn":[44.67325819],"iteration":7,"passed_time":0.1407157819,"remaining_time":3.377178767},
{"learn":[42.99884493],"iteration":8,"passed_time":0.1408399658,"remaining_time":2.988937052},
{"learn":[41.38668847],"iteration":9,"passed_time":0.1410521514,"remaining_time":2.679990876},
{"learn":[40.44280247],"iteration":10,"passed_time":0.1412022847,"remaining_time":2.426111983},
{"learn":[38.95121225],"iteration":11,"passed_time":0.1413560557,"remaining_time":2.214578206},
{"learn":[37.99980715],"iteration":12,"passed_time":0.1415438931,"remaining_time":2.036054462},
{"learn":[36.45364722],"iteration":13,"passed_time":0.1417166232,"remaining_time":1.882806566},
{"learn":[35.26447169],"iteration":14,"passed_time":0.1418055917,"remaining_time":1.748935631},
{"learn":[34.41734438],"iteration":15,"passed_time":0.1419811039,"remaining_time":1.632782695},
{"learn":[33.49199287],"iteration":16,"passed_time":0.1422352118,"remaining_time":1.531120221},
{"learn":[32.6986523],"iteration":17,"passed_time":0.1424783562,"remaining_time":1.440614491},
{"learn":[31.65152631],"iteration":18,"passed_time":0.1425678962,"remaining_time":1.358146801},
{"learn":[30.54256255],"iteration":19,"passed_time":0.1427547291,"remaining_time":1.284792562},
{"learn":[29.59101709],"iteration":20,"passed_time":0.1428396662,"remaining_time":1.217538107},
{"learn":[28.53218261],"iteration":21,"passed_time":0.1430402883,"remaining_time":1.157325969},
{"learn":[27.44063126],"iteration":22,"passed_time":0.1433010996,"remaining_time":1.102795419},
{"learn":[26.54107433],"iteration":23,"passed_time":0.1434466052,"remaining_time":1.051941772},
{"learn":[25.80699445],"iteration":24,"passed_time":0.1437025962,"remaining_time":1.005918173},
{"learn":[25.24368036],"iteration":25,"passed_time":0.1438903396,"remaining_time":0.9629584269},
{"learn":[24.49268522],"iteration":26,"passed_time":0.1439746246,"remaining_time":0.9225040764},
{"learn":[23.62762266],"iteration":27,"passed_time":0.1442901414,"remaining_time":0.8863537259},
{"learn":[22.85471011],"iteration":28,"passed_time":0.1444879935,"remaining_time":0.8519809274},
{"learn":[22.07846613],"iteration":29,"passed_time":0.1447317111,"remaining_time":0.8201463627},
{"learn":[21.57367912],"iteration":30,"passed_time":0.1449947197,"remaining_time":0.7904550846},
{"learn":[20.8698243],"iteration":31,"passed_time":0.1451152859,"remaining_time":0.7618552512},
{"learn":[20.38237284],"iteration":32,"passed_time":0.1452669949,"remaining_time":0.7351390349},
{"learn":[19.96958642],"iteration":33,"passed_time":0.1454107885,"remaining_time":0.7099467909},
{"learn":[19.52684524],"iteration":34,"passed_time":0.1456576982,"remaining_time":0.6866720057},
{"learn":[18.82306665],"iteration":35,"passed_time":0.1458447602,"remaining_time":0.6644039075},
{"learn":[18.39039073],"iteration":36,"passed_time":0.1459892075,"remaining_time":0.6431416439},
{"learn":[17.97191449],"iteration":37,"passed_time":0.1461326539,"remaining_time":0.6229865773},
{"learn":[17.41580457],"iteration":38,"passed_time":0.1462507617,"remaining_time":0.6037531444},
{"learn":[16.81527141],"iteration":39,"passed_time":0.1464447815,"remaining_time":0.585779126},
{"learn":[16.1918316],"iteration":40,"passed_time":0.1466307471,"remaining_time":0.5686411899},
{"learn":[15.79134982],"iteration":41,"passed_time":0.1468992406,"remaining_time":0.5526209528},
{"learn":[15.40507721],"iteration":42,"passed_time":0.1470886371,"remaining_time":0.5370445589},
{"learn":[15.08044532],"iteration":43,"passed_time":0.1472491107,"remaining_time":0.5220650289},
{"learn":[14.64149651],"iteration":44,"passed_time":0.1473663103,"remaining_time":0.5075950687},
{"learn":[14.22414805],"iteration":45,"passed_time":0.147502676,"remaining_time":0.4938133068},
{"learn":[13.75834794],"iteration":46,"passed_time":0.1476231352,"remaining_time":0.4805604188},
{"learn":[13.40010298],"iteration":47,"passed_time":0.1478701115,"remaining_time":0.4682553531},
{"learn":[13.08264632],"iteration":48,"passed_time":0.1480736829,"remaining_time":0.4563086964},
{"learn":[12.68255416],"iteration":49,"passed_time":0.1482633865,"remaining_time":0.4447901594},
{"learn":[12.39505054],"iteration":50,"passed_time":0.1484500712,"remaining_time":0.4337070708},
{"learn":[12.12831583],"iteration":51,"passed_time":0.1487107497,"remaining_time":0.4232536722},
{"learn":[11.73944891],"iteration":52,"passed_time":0.1488739214,"remaining_time":0.4129144613},
{"learn":[11.4794765],"iteration":53,"passed_time":0.1491133487,"remaining_time":0.4031583133},
{"learn":[11.21930107],"iteration":54,"passed_time":0.1492976187,"remaining_time":0.3936028129},
{"learn":[11.00466935],"iteration":55,"passed_time":0.1494538237,"remaining_time":0.3843098325},
{"learn":[10.74980182],"iteration":56,"passed_time":0.1497611306,"remaining_time":0.3757165205},
{"learn":[10.51127749],"iteration":57,"passed_time":0.1499204816,"remaining_time":0.3670466964},
{"learn":[10.09484807],"iteration":58,"passed_time":0.1501394252,"remaining_time":0.3588077788},
{"learn":[9.891596894],"iteration":59,"passed_time":0.1505845096,"remaining_time":0.3513638558},
{"learn":[9.689516059],"iteration":60,"passed_time":0.1513392684,"remaining_time":0.3448550541},
{"learn":[9.27984249],"iteration":61,"passed_time":0.1518773302,"remaining_time":0.3380495414},
{"learn":[8.936304483],"iteration":62,"passed_time":0.1521791003,"remaining_time":0.3309291546},
{"learn":[8.754666407],"iteration":63,"passed_time":0.1523893723,"remaining_time":0.3238274162},
{"learn":[8.593272706],"iteration":64,"passed_time":0.1525560191,"remaining_time":0.3168471166},
{"learn":[8.420570325],"iteration":65,"passed_time":0.1527244338,"remaining_time":0.3100768807},
{"learn":[8.254222169],"iteration":66,"passed_time":0.1530051044,"remaining_time":0.3037265506},
{"learn":[8.092934853],"iteration":67,"passed_time":0.1533500338,"remaining_time":0.2976794774},
{"learn":[7.921519505],"iteration":68,"passed_time":0.1536542881,"remaining_time":0.29172046},
{"learn":[7.756432467],"iteration":69,"passed_time":0.1538997811,"remaining_time":0.2858138792},
{"learn":[7.602395335],"iteration":70,"passed_time":0.154062336,"remaining_time":0.2799160752},
{"learn":[7.461302781],"iteration":71,"passed_time":0.1542912144,"remaining_time":0.2742954923},
{"learn":[7.143817876],"iteration":72,"passed_time":0.1545545244,"remaining_time":0.2688825287},
{"learn":[6.854110938],"iteration":73,"passed_time":0.1548644555,"remaining_time":0.2636881269},
{"learn":[6.72415212],"iteration":74,"passed_time":0.1550788078,"remaining_time":0.2584646797},
{"learn":[6.598221802],"iteration":75,"passed_time":0.1553566615,"remaining_time":0.2534766583},
{"learn":[6.476254653],"iteration":76,"passed_time":0.1555547813,"remaining_time":0.2484836117},
{"learn":[6.355989491],"iteration":77,"passed_time":0.1558159466,"remaining_time":0.2437121216},
{"learn":[6.239589029],"iteration":78,"passed_time":0.1560765633,"remaining_time":0.2390539767},
{"learn":[5.984345218],"iteration":79,"passed_time":0.1563343406,"remaining_time":0.2345015108},
{"learn":[5.869296931],"iteration":80,"passed_time":0.1568503036,"remaining_time":0.2304343967},
{"learn":[5.764370259],"iteration":81,"passed_time":0.1571575178,"remaining_time":0.2261535012},
{"learn":[5.661362194],"iteration":82,"passed_time":0.1577472631,"remaining_time":0.2223666238},
{"learn":[5.563035107],"iteration":83,"passed_time":0.1581087862,"remaining_time":0.2183407047},
{"learn":[5.467974324],"iteration":84,"passed_time":0.1584497203,"remaining_time":0.214373151},
{"learn":[5.374607125],"iteration":85,"passed_time":0.158824443,"remaining_time":0.2105347268},
{"learn":[5.285715017],"iteration":86,"passed_time":0.1592492516,"remaining_time":0.206840982},
{"learn":[5.064477547],"iteration":87,"passed_time":0.1595498839,"remaining_time":0.2030634886},
{"learn":[4.975329362],"iteration":88,"passed_time":0.1599203675,"remaining_time":0.1994512448},
{"learn":[4.889260474],"iteration":89,"passed_time":0.1602283517,"remaining_time":0.1958346521},
{"learn":[4.696860557],"iteration":90,"passed_time":0.1605125167,"remaining_time":0.1922622453},
{"learn":[4.615575582],"iteration":91,"passed_time":0.1607802337,"remaining_time":0.1887420135},
{"learn":[4.537081988],"iteration":92,"passed_time":0.1610663388,"remaining_time":0.1853128844},
{"learn":[4.355143277],"iteration":93,"passed_time":0.1613366455,"remaining_time":0.181932813},
{"learn":[4.281089595],"iteration":94,"passed_time":0.161608515,"remaining_time":0.1786199376},
{"learn":[4.209577896],"iteration":95,"passed_time":0.1618646785,"remaining_time":0.1753534017},
{"learn":[4.14053867],"iteration":96,"passed_time":0.1621186781,"remaining_time":0.1721466376},
{"learn":[3.981446382],"iteration":97,"passed_time":0.1624976939,"remaining_time":0.1691302528},
{"learn":[3.916178214],"iteration":98,"passed_time":0.1627625983,"remaining_time":0.1660507316},
{"learn":[3.849861707],"iteration":99,"passed_time":0.1630481371,"remaining_time":0.1630481371},
{"learn":[3.700202458],"iteration":100,"passed_time":0.1633056527,"remaining_time":0.1600718774},
{"learn":[3.637688558],"iteration":101,"passed_time":0.1635521302,"remaining_time":0.1571383211},
{"learn":[3.577448234],"iteration":102,"passed_time":0.1638180183,"remaining_time":0.1542752211},
{"learn":[3.519409537],"iteration":103,"passed_time":0.1640659281,"remaining_time":0.1514454721},
{"learn":[3.383454104],"iteration":104,"passed_time":0.1643555925,"remaining_time":0.1487026789},
{"learn":[3.328407596],"iteration":105,"passed_time":0.1646187468,"remaining_time":0.1459826622},
{"learn":[3.275369755],"iteration":106,"passed_time":0.164872571,"remaining_time":0.1433004589},
{"learn":[3.150541145],"iteration":107,"passed_time":0.1651430242,"remaining_time":0.140677391},
{"learn":[3.100231046],"iteration":108,"passed_time":0.1655615459,"remaining_time":0.1382211072},
{"learn":[3.051756949],"iteration":109,"passed_time":0.1658255936,"remaining_time":0.1356754856},
{"learn":[2.937141797],"iteration":110,"passed_time":0.1660746335,"remaining_time":0.1331589404},
{"learn":[2.891160263],"iteration":111,"passed_time":0.1664651016,"remaining_time":0.1307940084},
{"learn":[2.846859374],"iteration":112,"passed_time":0.1667368953,"remaining_time":0.1283726539},
{"learn":[2.741632892],"iteration":113,"passed_time":0.1670275955,"remaining_time":0.1260032738},
{"learn":[2.700959998],"iteration":114,"passed_time":0.1673584202,"remaining_time":0.1236997019},
{"learn":[2.66015735],"iteration":115,"passed_time":0.1675546714,"remaining_time":0.1213326931},
{"learn":[2.563441872],"iteration":116,"passed_time":0.1678391314,"remaining_time":0.1190653667},
{"learn":[2.526216601],"iteration":117,"passed_time":0.1681303943,"remaining_time":0.1168363757},
{"learn":[2.488997743],"iteration":118,"passed_time":0.1684192585,"remaining_time":0.1146383188},
{"learn":[2.402295726],"iteration":119,"passed_time":0.1686976363,"remaining_time":0.1124650909},
{"learn":[2.368321103],"iteration":120,"passed_time":0.1689421112,"remaining_time":0.1103010478},
{"learn":[2.335594913],"iteration":121,"passed_time":0.1699815534,"remaining_time":0.1086767309},
{"learn":[2.253052842],"iteration":122,"passed_time":0.1703641607,"remaining_time":0.1066507347},
{"learn":[2.221970613],"iteration":123,"passed_time":0.1706445512,"remaining_time":0.1045885959},
{"learn":[2.164892626],"iteration":124,"passed_time":0.1708966862,"remaining_time":0.1025380117},
{"learn":[2.111033682],"iteration":125,"passed_time":0.1712569298,"remaining_time":0.1005794667},
{"learn":[2.081867853],"iteration":126,"passed_time":0.1717651068,"remaining_time":0.09873112436},
{"learn":[2.011230579],"iteration":127,"passed_time":0.172069166,"remaining_time":0.09678890589},
{"learn":[1.962468577],"iteration":128,"passed_time":0.1723512558,"remaining_time":0.09485999349},
{"learn":[1.916428697],"iteration":129,"passed_time":0.1726113198,"remaining_time":0.09294455682},
{"learn":[1.890628915],"iteration":130,"passed_time":0.1728838074,"remaining_time":0.09106093671},
{"learn":[1.865811147],"iteration":131,"passed_time":0.1731489205,"remaining_time":0.08919792875},
{"learn":[1.841943682],"iteration":132,"passed_time":0.1734181449,"remaining_time":0.08736102035},
{"learn":[1.774167484],"iteration":133,"passed_time":0.1736900698,"remaining_time":0.08554884034},
{"learn":[1.733451063],"iteration":134,"passed_time":0.1739960257,"remaining_time":0.08377586424},
{"learn":[1.711480001],"iteration":135,"passed_time":0.1742922908,"remaining_time":0.08201990155},
{"learn":[1.690357572],"iteration":136,"passed_time":0.1745534107,"remaining_time":0.08026908669},
{"learn":[1.62848924],"iteration":137,"passed_time":0.1748202311,"remaining_time":0.07854242268},
{"learn":[1.591823797],"iteration":138,"passed_time":0.175123798,"remaining_time":0.07685288976},
{"learn":[1.55993374],"iteration":139,"passed_time":0.1753821335,"remaining_time":0.07516377149},
{"learn":[1.529175095],"iteration":140,"passed_time":0.1756459748,"remaining_time":0.07349725188},
{"learn":[1.499505617],"iteration":141,"passed_time":0.1759170634,"remaining_time":0.07185344841},
{"learn":[1.443922634],"iteration":142,"passed_time":0.1761711111,"remaining_time":0.07022205127},
{"learn":[1.415720663],"iteration":143,"passed_time":0.1764710953,"remaining_time":0.06862764816},
{"learn":[1.388502454],"iteration":144,"passed_time":0.1768048275,"remaining_time":0.0670639001},
{"learn":[1.362234569],"iteration":145,"passed_time":0.1770692721,"remaining_time":0.06549137461},
{"learn":[1.3368853],"iteration":146,"passed_time":0.177333768,"remaining_time":0.06393666465},
{"learn":[1.286918736],"iteration":147,"passed_time":0.1775938348,"remaining_time":0.06239783386},
{"learn":[1.262804685],"iteration":148,"passed_time":0.1778701888,"remaining_time":0.06088174248},
{"learn":[1.239528178],"iteration":149,"passed_time":0.1781271702,"remaining_time":0.05937572341},
{"learn":[1.198688201],"iteration":150,"passed_time":0.17840177,"remaining_time":0.0578919651},
{"learn":[1.176553157],"iteration":151,"passed_time":0.1786761177,"remaining_time":0.05642403717},
{"learn":[1.155183759],"iteration":152,"passed_time":0.178925329,"remaining_time":0.05496398996},
{"learn":[1.119317769],"iteration":153,"passed_time":0.1791885078,"remaining_time":0.05352383998},
{"learn":[1.099140365],"iteration":154,"passed_time":0.1794304121,"remaining_time":0.05209270029},
{"learn":[1.079660358],"iteration":155,"passed_time":0.1796883977,"remaining_time":0.05068134293},
{"learn":[1.060857265],"iteration":156,"passed_time":0.1800145051,"remaining_time":0.04930333579},
{"learn":[1.026466684],"iteration":157,"passed_time":0.1804270093,"remaining_time":0.04796161008},
{"learn":[1.008575018],"iteration":158,"passed_time":0.1808717868,"remaining_time":0.04663989471},
{"learn":[0.9913075389],"iteration":159,"passed_time":0.1811789311,"remaining_time":0.04529473277},
{"learn":[0.9599636449],"iteration":160,"passed_time":0.1815073642,"remaining_time":0.04396762239},
{"learn":[0.9436882445],"iteration":161,"passed_time":0.1817789917,"remaining_time":0.04263951658},
{"learn":[0.9279393683],"iteration":162,"passed_time":0.1820333589,"remaining_time":0.04132045571},
{"learn":[0.8988344917],"iteration":163,"passed_time":0.1823130162,"remaining_time":0.04001993039},
{"learn":[0.8726542286],"iteration":164,"passed_time":0.1827924652,"remaining_time":0.03877415929},
{"learn":[0.8580671465],"iteration":165,"passed_time":0.1830887155,"remaining_time":0.03750009835},
{"learn":[0.8439693489],"iteration":166,"passed_time":0.1833600356,"remaining_time":0.0362328214},
{"learn":[0.8204097855],"iteration":167,"passed_time":0.1836822337,"remaining_time":0.03498709213},
{"learn":[0.794437378],"iteration":168,"passed_time":0.1840775353,"remaining_time":0.03376570175},
{"learn":[0.7813763132],"iteration":169,"passed_time":0.1843573981,"remaining_time":0.03253365849},
{"learn":[0.7687685449],"iteration":170,"passed_time":0.1846180324,"remaining_time":0.03130949088},
{"learn":[0.748686868],"iteration":171,"passed_time":0.1848866933,"remaining_time":0.0300978338},
{"learn":[0.7366801565],"iteration":172,"passed_time":0.1851671164,"remaining_time":0.02889891412},
{"learn":[0.714639678],"iteration":173,"passed_time":0.1854529007,"remaining_time":0.02771135299},
{"learn":[0.6953128949],"iteration":174,"passed_time":0.185741925,"remaining_time":0.02653456072},
{"learn":[0.6842398042],"iteration":175,"passed_time":0.1859989667,"remaining_time":0.02536349546},
{"learn":[0.6734863438],"iteration":176,"passed_time":0.1862684062,"remaining_time":0.02420436916},
{"learn":[0.6524663345],"iteration":177,"passed_time":0.1865586224,"remaining_time":0.02305780726},
{"learn":[0.6358469731],"iteration":178,"passed_time":0.1868339574,"remaining_time":0.02191906763},
{"learn":[0.6272611527],"iteration":179,"passed_time":0.1871130829,"remaining_time":0.02079034255},
{"learn":[0.6189176585],"iteration":180,"passed_time":0.1873677575,"remaining_time":0.01966843863},
{"learn":[0.5999988133],"iteration":181,"passed_time":0.1876294152,"remaining_time":0.01855675535},
{"learn":[0.5921912417],"iteration":182,"passed_time":0.1879016319,"remaining_time":0.01745534285},
{"learn":[0.5847111402],"iteration":183,"passed_time":0.1881442233,"remaining_time":0.01636036724},
{"learn":[0.5775455455],"iteration":184,"passed_time":0.1885078891,"remaining_time":0.01528442344},
{"learn":[0.5615690686],"iteration":185,"passed_time":0.1888066364,"remaining_time":0.0142112522},
{"learn":[0.555107525],"iteration":186,"passed_time":0.189081802,"remaining_time":0.0131447242},
{"learn":[0.5486685586],"iteration":187,"passed_time":0.1894034816,"remaining_time":0.01208958393},
{"learn":[0.5425033211],"iteration":188,"passed_time":0.1896836819,"remaining_time":0.01103979101},
{"learn":[0.5280776003],"iteration":189,"passed_time":0.1899970154,"remaining_time":0.009999842917},
{"learn":[0.5225066943],"iteration":190,"passed_time":0.1902743314,"remaining_time":0.00896580619},
{"learn":[0.5044346457],"iteration":191,"passed_time":0.1907774788,"remaining_time":0.007949061618},
{"learn":[0.499144243],"iteration":192,"passed_time":0.191078842,"remaining_time":0.006930320694},
{"learn":[0.4846987325],"iteration":193,"passed_time":0.1913804034,"remaining_time":0.005918981548},
{"learn":[0.4796867095],"iteration":194,"passed_time":0.1916807528,"remaining_time":0.004914891097},
{"learn":[0.4748835056],"iteration":195,"passed_time":0.1919854176,"remaining_time":0.003918069748},
{"learn":[0.462795456],"iteration":196,"passed_time":0.1922812645,"remaining_time":0.002928141084},
{"learn":[0.4466876242],"iteration":197,"passed_time":0.1925574162,"remaining_time":0.001945024406},
{"learn":[0.4422200092],"iteration":198,"passed_time":0.1928679389,"remaining_time":0.0009691856225},
{"learn":[0.437939135],"iteration":199,"passed_time":0.1931536578,"remaining_time":0}
]}